fiable_db.py
fiabledb.py
fiabledb-1.0.0.dist-info/licenses/LICENCE
fiabledb-1.0.0.dist-info/METADATA
fiabledb-1.0.0.dist-info/WHEEL
fiabledb-1.0.0.dist-info/top_level.txt
fiabledb-1.0.0.dist-info/RECORD
