Metadata-Version: 2.4
Name: fiabledb
Version: 1.0.0
Summary: Immutable NoSQL database in a plain file
Home-page: https://github.com/tanrax/fiableDB
Author: Andros Fenollosa
Author-email: andros@fenollosa.email
Requires-Python: >3.7
License-File: LICENCE
Requires-Dist: ruff>=0.11.11
Requires-Dist: setuptools>=80.8.0
Requires-Dist: twine>=6.1.0
Requires-Dist: wheel>=0.45.1
Dynamic: author
Dynamic: author-email
Dynamic: home-page
Dynamic: license-file
Dynamic: requires-python
